solvate_step/__init__.py
solvate_step/_version.py
solvate_step/solvate.py
solvate_step/solvate_parameters.py
solvate_step/solvate_step.py
solvate_step/tk_solvate.py
solvate_step-0.9.3.dist-info/AUTHORS.rst
solvate_step-0.9.3.dist-info/LICENSE
solvate_step-0.9.3.dist-info/METADATA
solvate_step-0.9.3.dist-info/WHEEL
solvate_step-0.9.3.dist-info/entry_points.txt
solvate_step-0.9.3.dist-info/top_level.txt
solvate_step-0.9.3.dist-info/RECORD
