Metadata-Version: 2.1
Name: solvate-step
Version: 0.9.3
Summary: solvate_step
Home-page: https://github.com/molssi-seam/solvate_step
Author: Paul Saxe
Author-email: psaxe@molssi.org
License: BSD-3-Clause
Keywords: solvate_step
Platform: Linux
Platform: Mac OS-X
Platform: Unix
Platform: Windows
Classifier: Development Status :: 2 - Pre-Alpha
Classifier: Intended Audience :: Science/Research
Classifier: License :: OSI Approved :: BSD License
Classifier: Natural Language :: English
Classifier: Programming Language :: Python :: 3 :: Only
Classifier: Programming Language :: Python :: 3.6
Classifier: Programming Language :: Python :: 3.7
Requires-Dist: mendeleev
Requires-Dist: Pmw
Requires-Dist: seamm (>=0.9)
Requires-Dist: seamm-widgets (>=0.9)
Requires-Dist: seamm-util (>=0.9)
